LICENSE
README.md
pyproject.toml
setup.py
pdpy_lib/__init__.py
pdpy_lib.egg-info/PKG-INFO
pdpy_lib.egg-info/SOURCES.txt
pdpy_lib.egg-info/dependency_links.txt
pdpy_lib.egg-info/top_level.txt
pdpy_lib/connections/__init__.py
pdpy_lib/connections/edge.py
pdpy_lib/connections/iolet.py
pdpy_lib/core/__init__.py
pdpy_lib/core/base.py
pdpy_lib/core/canvasbase.py
pdpy_lib/core/message.py
pdpy_lib/core/object.py
pdpy_lib/encoding/__init__.py
pdpy_lib/encoding/pdpyencoder.py
pdpy_lib/encoding/pdpyparser-2.py
pdpy_lib/encoding/pdpyparser-3.py
pdpy_lib/encoding/pdpyparser-4.py
pdpy_lib/encoding/xmlbuilder.py
pdpy_lib/encoding/xmltagconvert.py
pdpy_lib/extra/__init__.py
pdpy_lib/extra/arranger.py
pdpy_lib/extra/translator.py
pdpy_lib/iemgui/__init__.py
pdpy_lib/iemgui/bng.py
pdpy_lib/iemgui/cnv.py
pdpy_lib/iemgui/iemfont.py
pdpy_lib/iemgui/iemlabel.py
pdpy_lib/iemgui/nbx.py
pdpy_lib/iemgui/radio.py
pdpy_lib/iemgui/slider.py
pdpy_lib/iemgui/toggle.py
pdpy_lib/iemgui/vu.py
pdpy_lib/memory/__init__.py
pdpy_lib/memory/array.py
pdpy_lib/memory/data.py
pdpy_lib/memory/goparray.py
pdpy_lib/memory/graph.py
pdpy_lib/memory/scalar.py
pdpy_lib/memory/struct.py
pdpy_lib/memory/types.py
pdpy_lib/objects/__init__.py
pdpy_lib/objects/comment.py
pdpy_lib/objects/gui.py
pdpy_lib/objects/msg.py
pdpy_lib/objects/obj.py
pdpy_lib/parse/__init__.py
pdpy_lib/parse/pdpy2json.py
pdpy_lib/parse/pdpyparser.py
pdpy_lib/parse/pdpyxmlparser.py
pdpy_lib/patching/__init__.py
pdpy_lib/patching/canvas.py
pdpy_lib/patching/comm.py
pdpy_lib/patching/dependencies.py
pdpy_lib/patching/patch.py
pdpy_lib/patching/pdpy.py
pdpy_lib/primitives/__init__.py
pdpy_lib/primitives/area.py
pdpy_lib/primitives/bounds.py
pdpy_lib/primitives/coords.py
pdpy_lib/primitives/point.py
pdpy_lib/primitives/size.py
pdpy_lib/utilities/__init__.py
pdpy_lib/utilities/arrange.py
pdpy_lib/utilities/arrange1.py
pdpy_lib/utilities/arrange1a.py
pdpy_lib/utilities/arrange1b.py
pdpy_lib/utilities/arrange2.py
pdpy_lib/utilities/default.py
pdpy_lib/utilities/exceptions.py
pdpy_lib/utilities/namespace.py
pdpy_lib/utilities/regex.py
pdpy_lib/utilities/utils.py