Metadata-Version: 2.1
Name: pdpy-lib
Version: 0.1.6
Summary: A Pure Data PYthon Utility
Author-email: Fede Camara Halac <fdch@nyu.edu>
Project-URL: Homepage, https://github.com/pdpy-org/pdpy
Project-URL: Bug Tracker, https://github.com/pdpy-org/pdpy/issues
Classifier: Topic :: Multimedia
Classifier: Programming Language :: Python :: 3
Classifier: License :: OSI Approved :: GNU General Public License (GPL)
Classifier: Operating System :: OS Independent
Requires-Python: >=3.7
License-File: LICENSE
